{
  "type": "File",
  "start": 0,
  "end": 120,
  "loc": {
    "start": {
      "line": 1,
      "column": 0
    },
    "end": {
      "line": 9,
      "column": 27
    }
  },
  "program": {
    "type": "Program",
    "start": 0,
    "end": 120,
    "loc": {
      "start": {
        "line": 1,
        "column": 0
      },
      "end": {
        "line": 9,
        "column": 27
      }
    },
    "sourceType": "module",
    "body": [
      {
        "type": "VariableDeclaration",
        "start": 23,
        "end": 42,
        "loc": {
          "start": {
            "line": 3,
            "column": 0
          },
          "end": {
            "line": 3,
            "column": 19
          }
        },
        "declarations": [
          {
            "type": "VariableDeclarator",
            "start": 27,
            "end": 41,
            "loc": {
              "start": {
                "line": 3,
                "column": 4
              },
              "end": {
                "line": 3,
                "column": 18
              }
            },
            "id": {
              "type": "Identifier",
              "start": 27,
              "end": 36,
              "loc": {
                "start": {
                  "line": 3,
                  "column": 4
                },
                "end": {
                  "line": 3,
                  "column": 13
                },
                "identifierName": "Abilities"
              },
              "name": "Abilities",
              "leadingComments": null
            },
            "init": {
              "type": "ObjectExpression",
              "start": 39,
              "end": 41,
              "loc": {
                "start": {
                  "line": 3,
                  "column": 16
                },
                "end": {
                  "line": 3,
                  "column": 18
                }
              },
              "properties": []
            },
            "leadingComments": null
          }
        ],
        "kind": "let",
        "leadingComments": [
          {
            "type": "CommentBlock",
            "value": " global module ",
            "start": 0,
            "end": 19,
            "loc": {
              "start": {
                "line": 1,
                "column": 0
              },
              "end": {
                "line": 1,
                "column": 19
              }
            }
          }
        ]
      },
      {
        "type": "ExpressionStatement",
        "start": 46,
        "end": 66,
        "loc": {
          "start": {
            "line": 5,
            "column": 0
          },
          "end": {
            "line": 5,
            "column": 20
          }
        },
        "expression": {
          "type": "AssignmentExpression",
          "start": 46,
          "end": 65,
          "loc": {
            "start": {
              "line": 5,
              "column": 0
            },
            "end": {
              "line": 5,
              "column": 19
            }
          },
          "operator": "=",
          "left": {
            "type": "MemberExpression",
            "start": 46,
            "end": 60,
            "loc": {
              "start": {
                "line": 5,
                "column": 0
              },
              "end": {
                "line": 5,
                "column": 14
              }
            },
            "object": {
              "type": "Identifier",
              "start": 46,
              "end": 55,
              "loc": {
                "start": {
                  "line": 5,
                  "column": 0
                },
                "end": {
                  "line": 5,
                  "column": 9
                },
                "identifierName": "Abilities"
              },
              "name": "Abilities"
            },
            "property": {
              "type": "Identifier",
              "start": 56,
              "end": 60,
              "loc": {
                "start": {
                  "line": 5,
                  "column": 10
                },
                "end": {
                  "line": 5,
                  "column": 14
                },
                "identifierName": "Data"
              },
              "name": "Data"
            },
            "computed": false
          },
          "right": {
            "type": "ObjectExpression",
            "start": 63,
            "end": 65,
            "loc": {
              "start": {
                "line": 5,
                "column": 17
              },
              "end": {
                "line": 5,
                "column": 19
              }
            },
            "properties": []
          }
        }
      },
      {
        "type": "ExpressionStatement",
        "start": 68,
        "end": 87,
        "loc": {
          "start": {
            "line": 6,
            "column": 0
          },
          "end": {
            "line": 6,
            "column": 19
          }
        },
        "expression": {
          "type": "AssignmentExpression",
          "start": 68,
          "end": 86,
          "loc": {
            "start": {
              "line": 6,
              "column": 0
            },
            "end": {
              "line": 6,
              "column": 18
            }
          },
          "operator": "=",
          "left": {
            "type": "MemberExpression",
            "start": 68,
            "end": 81,
            "loc": {
              "start": {
                "line": 6,
                "column": 0
              },
              "end": {
                "line": 6,
                "column": 13
              }
            },
            "object": {
              "type": "Identifier",
              "start": 68,
              "end": 77,
              "loc": {
                "start": {
                  "line": 6,
                  "column": 0
                },
                "end": {
                  "line": 6,
                  "column": 9
                },
                "identifierName": "Abilities"
              },
              "name": "Abilities"
            },
            "property": {
              "type": "Identifier",
              "start": 78,
              "end": 81,
              "loc": {
                "start": {
                  "line": 6,
                  "column": 10
                },
                "end": {
                  "line": 6,
                  "column": 13
                },
                "identifierName": "Ids"
              },
              "name": "Ids"
            },
            "computed": false
          },
          "right": {
            "type": "ObjectExpression",
            "start": 84,
            "end": 86,
            "loc": {
              "start": {
                "line": 6,
                "column": 16
              },
              "end": {
                "line": 6,
                "column": 18
              }
            },
            "properties": []
          }
        }
      },
      {
        "type": "ExpressionStatement",
        "start": 93,
        "end": 120,
        "loc": {
          "start": {
            "line": 9,
            "column": 0
          },
          "end": {
            "line": 9,
            "column": 27
          }
        },
        "expression": {
          "type": "AssignmentExpression",
          "start": 93,
          "end": 119,
          "loc": {
            "start": {
              "line": 9,
              "column": 0
            },
            "end": {
              "line": 9,
              "column": 26
            }
          },
          "operator": "=",
          "left": {
            "type": "MemberExpression",
            "start": 93,
            "end": 107,
            "loc": {
              "start": {
                "line": 9,
                "column": 0
              },
              "end": {
                "line": 9,
                "column": 14
              }
            },
            "object": {
              "type": "Identifier",
              "start": 93,
              "end": 99,
              "loc": {
                "start": {
                  "line": 9,
                  "column": 0
                },
                "end": {
                  "line": 9,
                  "column": 6
                },
                "identifierName": "module"
              },
              "name": "module"
            },
            "property": {
              "type": "Identifier",
              "start": 100,
              "end": 107,
              "loc": {
                "start": {
                  "line": 9,
                  "column": 7
                },
                "end": {
                  "line": 9,
                  "column": 14
                },
                "identifierName": "exports"
              },
              "name": "exports"
            },
            "computed": false
          },
          "right": {
            "type": "Identifier",
            "start": 110,
            "end": 119,
            "loc": {
              "start": {
                "line": 9,
                "column": 17
              },
              "end": {
                "line": 9,
                "column": 26
              },
              "identifierName": "Abilities"
            },
            "name": "Abilities"
          }
        }
      }
    ],
    "directives": []
  },
  "comments": [
    {
      "type": "CommentBlock",
      "value": " global module ",
      "start": 0,
      "end": 19,
      "loc": {
        "start": {
          "line": 1,
          "column": 0
        },
        "end": {
          "line": 1,
          "column": 19
        }
      }
    }
  ],
  "tokens": [
    {
      "type": "CommentBlock",
      "value": " global module ",
      "start": 0,
      "end": 19,
      "loc": {
        "start": {
          "line": 1,
          "column": 0
        },
        "end": {
          "line": 1,
          "column": 19
        }
      }
    },
    {
      "type": {
        "label": "let",
        "keyword": "let",
        "beforeExpr": false,
        "startsExpr": false,
        "rightAssociative": false,
        "isLoop": false,
        "isAssign": false,
        "prefix": false,
        "postfix": false,
        "binop": null,
        "updateContext": null
      },
      "value": "let",
      "start": 23,
      "end": 26,
      "loc": {
        "start": {
          "line": 3,
          "column": 0
        },
        "end": {
          "line": 3,
          "column": 3
        }
      }
    },
    {
      "type": {
        "label": "name",
        "beforeExpr": false,
        "startsExpr": true,
        "rightAssociative": false,
        "isLoop": false,
        "isAssign": false,
        "prefix": false,
        "postfix": false,
        "binop": null
      },
      "value": "Abilities",
      "start": 27,
      "end": 36,
      "loc": {
        "start": {
          "line": 3,
          "column": 4
        },
        "end": {
          "line": 3,
          "column": 13
        }
      }
    },
    {
      "type": {
        "label": "=",
        "beforeExpr": true,
        "startsExpr": false,
        "rightAssociative": false,
        "isLoop": false,
        "isAssign": true,
        "prefix": false,
        "postfix": false,
        "binop": null,
        "updateContext": null
      },
      "value": "=",
      "start": 37,
      "end": 38,
      "loc": {
        "start": {
          "line": 3,
          "column": 14
        },
        "end": {
          "line": 3,
          "column": 15
        }
      }
    },
    {
      "type": {
        "label": "{",
        "beforeExpr": true,
        "startsExpr": true,
        "rightAssociative": false,
        "isLoop": false,
        "isAssign": false,
        "prefix": false,
        "postfix": false,
        "binop": null
      },
      "start": 39,
      "end": 40,
      "loc": {
        "start": {
          "line": 3,
          "column": 16
        },
        "end": {
          "line": 3,
          "column": 17
        }
      }
    },
    {
      "type": {
        "label": "}",
        "beforeExpr": false,
        "startsExpr": false,
        "rightAssociative": false,
        "isLoop": false,
        "isAssign": false,
        "prefix": false,
        "postfix": false,
        "binop": null
      },
      "start": 40,
      "end": 41,
      "loc": {
        "start": {
          "line": 3,
          "column": 17
        },
        "end": {
          "line": 3,
          "column": 18
        }
      }
    },
    {
      "type": {
        "label": ";",
        "beforeExpr": true,
        "startsExpr": false,
        "rightAssociative": false,
        "isLoop": false,
        "isAssign": false,
        "prefix": false,
        "postfix": false,
        "binop": null,
        "updateContext": null
      },
      "start": 41,
      "end": 42,
      "loc": {
        "start": {
          "line": 3,
          "column": 18
        },
        "end": {
          "line": 3,
          "column": 19
        }
      }
    },
    {
      "type": {
        "label": "name",
        "beforeExpr": false,
        "startsExpr": true,
        "rightAssociative": false,
        "isLoop": false,
        "isAssign": false,
        "prefix": false,
        "postfix": false,
        "binop": null
      },
      "value": "Abilities",
      "start": 46,
      "end": 55,
      "loc": {
        "start": {
          "line": 5,
          "column": 0
        },
        "end": {
          "line": 5,
          "column": 9
        }
      }
    },
    {
      "type": {
        "label": ".",
        "beforeExpr": false,
        "startsExpr": false,
        "rightAssociative": false,
        "isLoop": false,
        "isAssign": false,
        "prefix": false,
        "postfix": false,
        "binop": null,
        "updateContext": null
      },
      "start": 55,
      "end": 56,
      "loc": {
        "start": {
          "line": 5,
          "column": 9
        },
        "end": {
          "line": 5,
          "column": 10
        }
      }
    },
    {
      "type": {
        "label": "name",
        "beforeExpr": false,
        "startsExpr": true,
        "rightAssociative": false,
        "isLoop": false,
        "isAssign": false,
        "prefix": false,
        "postfix": false,
        "binop": null
      },
      "value": "Data",
      "start": 56,
      "end": 60,
      "loc": {
        "start": {
          "line": 5,
          "column": 10
        },
        "end": {
          "line": 5,
          "column": 14
        }
      }
    },
    {
      "type": {
        "label": "=",
        "beforeExpr": true,
        "startsExpr": false,
        "rightAssociative": false,
        "isLoop": false,
        "isAssign": true,
        "prefix": false,
        "postfix": false,
        "binop": null,
        "updateContext": null
      },
      "value": "=",
      "start": 61,
      "end": 62,
      "loc": {
        "start": {
          "line": 5,
          "column": 15
        },
        "end": {
          "line": 5,
          "column": 16
        }
      }
    },
    {
      "type": {
        "label": "{",
        "beforeExpr": true,
        "startsExpr": true,
        "rightAssociative": false,
        "isLoop": false,
        "isAssign": false,
        "prefix": false,
        "postfix": false,
        "binop": null
      },
      "start": 63,
      "end": 64,
      "loc": {
        "start": {
          "line": 5,
          "column": 17
        },
        "end": {
          "line": 5,
          "column": 18
        }
      }
    },
    {
      "type": {
        "label": "}",
        "beforeExpr": false,
        "startsExpr": false,
        "rightAssociative": false,
        "isLoop": false,
        "isAssign": false,
        "prefix": false,
        "postfix": false,
        "binop": null
      },
      "start": 64,
      "end": 65,
      "loc": {
        "start": {
          "line": 5,
          "column": 18
        },
        "end": {
          "line": 5,
          "column": 19
        }
      }
    },
    {
      "type": {
        "label": ";",
        "beforeExpr": true,
        "startsExpr": false,
        "rightAssociative": false,
        "isLoop": false,
        "isAssign": false,
        "prefix": false,
        "postfix": false,
        "binop": null,
        "updateContext": null
      },
      "start": 65,
      "end": 66,
      "loc": {
        "start": {
          "line": 5,
          "column": 19
        },
        "end": {
          "line": 5,
          "column": 20
        }
      }
    },
    {
      "type": {
        "label": "name",
        "beforeExpr": false,
        "startsExpr": true,
        "rightAssociative": false,
        "isLoop": false,
        "isAssign": false,
        "prefix": false,
        "postfix": false,
        "binop": null
      },
      "value": "Abilities",
      "start": 68,
      "end": 77,
      "loc": {
        "start": {
          "line": 6,
          "column": 0
        },
        "end": {
          "line": 6,
          "column": 9
        }
      }
    },
    {
      "type": {
        "label": ".",
        "beforeExpr": false,
        "startsExpr": false,
        "rightAssociative": false,
        "isLoop": false,
        "isAssign": false,
        "prefix": false,
        "postfix": false,
        "binop": null,
        "updateContext": null
      },
      "start": 77,
      "end": 78,
      "loc": {
        "start": {
          "line": 6,
          "column": 9
        },
        "end": {
          "line": 6,
          "column": 10
        }
      }
    },
    {
      "type": {
        "label": "name",
        "beforeExpr": false,
        "startsExpr": true,
        "rightAssociative": false,
        "isLoop": false,
        "isAssign": false,
        "prefix": false,
        "postfix": false,
        "binop": null
      },
      "value": "Ids",
      "start": 78,
      "end": 81,
      "loc": {
        "start": {
          "line": 6,
          "column": 10
        },
        "end": {
          "line": 6,
          "column": 13
        }
      }
    },
    {
      "type": {
        "label": "=",
        "beforeExpr": true,
        "startsExpr": false,
        "rightAssociative": false,
        "isLoop": false,
        "isAssign": true,
        "prefix": false,
        "postfix": false,
        "binop": null,
        "updateContext": null
      },
      "value": "=",
      "start": 82,
      "end": 83,
      "loc": {
        "start": {
          "line": 6,
          "column": 14
        },
        "end": {
          "line": 6,
          "column": 15
        }
      }
    },
    {
      "type": {
        "label": "{",
        "beforeExpr": true,
        "startsExpr": true,
        "rightAssociative": false,
        "isLoop": false,
        "isAssign": false,
        "prefix": false,
        "postfix": false,
        "binop": null
      },
      "start": 84,
      "end": 85,
      "loc": {
        "start": {
          "line": 6,
          "column": 16
        },
        "end": {
          "line": 6,
          "column": 17
        }
      }
    },
    {
      "type": {
        "label": "}",
        "beforeExpr": false,
        "startsExpr": false,
        "rightAssociative": false,
        "isLoop": false,
        "isAssign": false,
        "prefix": false,
        "postfix": false,
        "binop": null
      },
      "start": 85,
      "end": 86,
      "loc": {
        "start": {
          "line": 6,
          "column": 17
        },
        "end": {
          "line": 6,
          "column": 18
        }
      }
    },
    {
      "type": {
        "label": ";",
        "beforeExpr": true,
        "startsExpr": false,
        "rightAssociative": false,
        "isLoop": false,
        "isAssign": false,
        "prefix": false,
        "postfix": false,
        "binop": null,
        "updateContext": null
      },
      "start": 86,
      "end": 87,
      "loc": {
        "start": {
          "line": 6,
          "column": 18
        },
        "end": {
          "line": 6,
          "column": 19
        }
      }
    },
    {
      "type": {
        "label": "name",
        "beforeExpr": false,
        "startsExpr": true,
        "rightAssociative": false,
        "isLoop": false,
        "isAssign": false,
        "prefix": false,
        "postfix": false,
        "binop": null
      },
      "value": "module",
      "start": 93,
      "end": 99,
      "loc": {
        "start": {
          "line": 9,
          "column": 0
        },
        "end": {
          "line": 9,
          "column": 6
        }
      }
    },
    {
      "type": {
        "label": ".",
        "beforeExpr": false,
        "startsExpr": false,
        "rightAssociative": false,
        "isLoop": false,
        "isAssign": false,
        "prefix": false,
        "postfix": false,
        "binop": null,
        "updateContext": null
      },
      "start": 99,
      "end": 100,
      "loc": {
        "start": {
          "line": 9,
          "column": 6
        },
        "end": {
          "line": 9,
          "column": 7
        }
      }
    },
    {
      "type": {
        "label": "name",
        "beforeExpr": false,
        "startsExpr": true,
        "rightAssociative": false,
        "isLoop": false,
        "isAssign": false,
        "prefix": false,
        "postfix": false,
        "binop": null
      },
      "value": "exports",
      "start": 100,
      "end": 107,
      "loc": {
        "start": {
          "line": 9,
          "column": 7
        },
        "end": {
          "line": 9,
          "column": 14
        }
      }
    },
    {
      "type": {
        "label": "=",
        "beforeExpr": true,
        "startsExpr": false,
        "rightAssociative": false,
        "isLoop": false,
        "isAssign": true,
        "prefix": false,
        "postfix": false,
        "binop": null,
        "updateContext": null
      },
      "value": "=",
      "start": 108,
      "end": 109,
      "loc": {
        "start": {
          "line": 9,
          "column": 15
        },
        "end": {
          "line": 9,
          "column": 16
        }
      }
    },
    {
      "type": {
        "label": "name",
        "beforeExpr": false,
        "startsExpr": true,
        "rightAssociative": false,
        "isLoop": false,
        "isAssign": false,
        "prefix": false,
        "postfix": false,
        "binop": null
      },
      "value": "Abilities",
      "start": 110,
      "end": 119,
      "loc": {
        "start": {
          "line": 9,
          "column": 17
        },
        "end": {
          "line": 9,
          "column": 26
        }
      }
    },
    {
      "type": {
        "label": ";",
        "beforeExpr": true,
        "startsExpr": false,
        "rightAssociative": false,
        "isLoop": false,
        "isAssign": false,
        "prefix": false,
        "postfix": false,
        "binop": null,
        "updateContext": null
      },
      "start": 119,
      "end": 120,
      "loc": {
        "start": {
          "line": 9,
          "column": 26
        },
        "end": {
          "line": 9,
          "column": 27
        }
      }
    },
    {
      "type": {
        "label": "eof",
        "beforeExpr": false,
        "startsExpr": false,
        "rightAssociative": false,
        "isLoop": false,
        "isAssign": false,
        "prefix": false,
        "postfix": false,
        "binop": null,
        "updateContext": null
      },
      "start": 120,
      "end": 120,
      "loc": {
        "start": {
          "line": 9,
          "column": 27
        },
        "end": {
          "line": 9,
          "column": 27
        }
      }
    }
  ]
}